petra/__init__.py
petra/aux_distributions.py
petra/cost_matrix.py
petra/initialization.py
petra/make_catalog.py
petra/parametric_fits.py
petra/posterior_chain.py
petra/relabel.py
petra/samples_io.py
petra/utils.py
petra_catalogs-1.0.0.dist-info/LICENSE
petra_catalogs-1.0.0.dist-info/METADATA
petra_catalogs-1.0.0.dist-info/WHEEL
petra_catalogs-1.0.0.dist-info/RECORD
